pyopentts/__init__.py
pyopentts/cache.py
pyopentts/misc.py
pyopentts-0.1.2.dist-info/METADATA
pyopentts-0.1.2.dist-info/WHEEL
pyopentts-0.1.2.dist-info/top_level.txt
pyopentts-0.1.2.dist-info/RECORD
